nonebot_plugin_orangejuice/Card.py
nonebot_plugin_orangejuice/Config.py
nonebot_plugin_orangejuice/Emote.py
nonebot_plugin_orangejuice/Ess.py
nonebot_plugin_orangejuice/Le.py
nonebot_plugin_orangejuice/Mixer.py
nonebot_plugin_orangejuice/Stats.py
nonebot_plugin_orangejuice/__init__.py
nonebot_plugin_orangejuice-1.1.0.dist-info/licenses/LICENSE
nonebot_plugin_orangejuice-1.1.0.dist-info/METADATA
nonebot_plugin_orangejuice-1.1.0.dist-info/WHEEL
nonebot_plugin_orangejuice-1.1.0.dist-info/top_level.txt
nonebot_plugin_orangejuice-1.1.0.dist-info/RECORD
