Metadata-Version: 2.4
Name: nonebot-plugin-orangejuice
Version: 1.1.0
Summary: Sorabot Implemention
Author-email: Polaris_Light <995905922@qq.com>
License-Expression: MIT
Project-URL: Homepage, https://github.com/FDCraft/nonebot-plugin-orangejuice
Keywords: orangejuice
Requires-Python: >=3.8
License-File: LICENSE
Requires-Dist: nonebot2>=2.0.0
Requires-Dist: nonebot-adapter-onebot>=2.0.0-beta.1
Requires-Dist: nonebot-plugin-apscheduler>=0.4.0
Requires-Dist: cachetools>=5.0.0
Requires-Dist: aiohttp>=3.8.0
Requires-Dist: aiosqlite>=0.20.0
Requires-Dist: FuzzyWuzzy>=0.18.0
Requires-Dist: python-Levenshtein>=0.25.0
Dynamic: license-file
